reapit_cdk/userpool_domain/__init__.py
reapit_cdk/userpool_domain/py.typed
reapit_cdk/userpool_domain/_jsii/__init__.py
reapit_cdk/userpool_domain/_jsii/userpool-domain@0.1.2.jsii.tgz
reapit_cdk.userpool_domain-0.1.2.dist-info/LICENSE
reapit_cdk.userpool_domain-0.1.2.dist-info/METADATA
reapit_cdk.userpool_domain-0.1.2.dist-info/WHEEL
reapit_cdk.userpool_domain-0.1.2.dist-info/top_level.txt
reapit_cdk.userpool_domain-0.1.2.dist-info/RECORD
