Metadata-Version: 2.1
Name: reapit-cdk.userpool-domain
Version: 0.1.2
Summary: This construct returns the given Cognito UserPool's UserPoolDomain, or creates one. This resolves an issue with [AWS::Cognito::UserPoolDomain](https://docs.aws.amazon.com/AWSCloudFormation/latest/UserGuide/aws-resource-cognito-userpooldomain.html), since that will fail if one already exists.
Home-page: https://github.com/reapit/ts-cdk-constructs/blob/main/packages/constructs/userpool-domain
Author: Josh Balfour<jbalfour@reapit.com>
License: MIT
Project-URL: Source, https://github.com/reapit/ts-cdk-constructs.git
Platform: UNKNOWN
Classifier: Intended Audience :: Developers
Classifier: Operating System :: OS Independent
Classifier: Programming Language :: JavaScript
Classifier: Programming Language :: Python :: 3 :: Only
Classifier: Programming Language :: Python :: 3.8
Classifier: Programming Language :: Python :: 3.9
Classifier: Programming Language :: Python :: 3.10
Classifier: Programming Language :: Python :: 3.11
Classifier: Typing :: Typed
Classifier: Development Status :: 5 - Production/Stable
Classifier: License :: OSI Approved
Requires-Python: ~=3.8
License-File: LICENSE
Requires-Dist: aws-cdk-lib (<3.0.0,>=2.96.2)
Requires-Dist: constructs (<11.0.0,>=10.2.70)
Requires-Dist: jsii (<2.0.0,>=1.94.0)
Requires-Dist: publication (>=0.0.3)
Requires-Dist: typeguard (~=2.13.3)
